[
    {
        "key": "dbln",
        "value": "%7B%22100074474806537%22%3A%22zZNcqjTD%22%7D",
        "domain": "facebook.com",
        "path": "/login/device-based/",
        "hostOnly": false,
        "creation": "2022-11-30T15:49:53.985Z",
        "lastAccessed": "2022-11-30T15:49:53.987Z"
    },
    {
        "key": "datr",
        "value": "d3uHYy4VHG9jDVnGheaiX2wG",
        "domain": "facebook.com",
        "path": "/",
        "hostOnly": false,
        "creation": "2022-11-30T15:49:53.987Z",
        "lastAccessed": "2022-11-30T15:49:53.987Z"
    },
    {
        "key": "sb",
        "value": "d3uHY6x1Dze-nPcu4-6ItHgy",
        "domain": "facebook.com",
        "path": "/",
        "hostOnly": false,
        "creation": "2022-11-30T15:49:53.987Z",
        "lastAccessed": "2022-11-30T15:49:53.987Z"
    },
    {
        "key": "m_pixel_ratio",
        "value": "1.875",
        "domain": "facebook.com",
        "path": "/",
        "hostOnly": false,
        "creation": "2022-11-30T15:49:53.987Z",
        "lastAccessed": "2022-11-30T15:49:53.987Z"
    },
    {
        "key": "fr",
        "value": "0RP3E0wxzFB1Bammn.AWUuoLDXbkqvaqeO7-71P2yfc3c.Bjh3t3.l3.AAA.0.0.Bjh3uI.AWWmUOm_y5s",
        "domain": "facebook.com",
        "path": "/",
        "hostOnly": false,
        "creation": "2022-11-30T15:49:53.987Z",
        "lastAccessed": "2022-11-30T15:49:53.987Z"
    },
    {
        "key": "c_user",
        "value": "100074474806537",
        "domain": "facebook.com",
        "path": "/",
        "hostOnly": false,
        "creation": "2022-11-30T15:49:53.987Z",
        "lastAccessed": "2022-11-30T15:49:53.987Z"
    },
    {
        "key": "xs",
        "value": "6%3AIJArqBmzDLOe_A%3A2%3A1669823368%3A-1%3A6299",
        "domain": "facebook.com",
        "path": "/",
        "hostOnly": false,
        "creation": "2022-11-30T15:49:53.987Z",
        "lastAccessed": "2022-11-30T15:49:53.988Z"
    },
    {
        "key": "m_page_voice",
        "value": "100074474806537",
        "domain": "facebook.com",
        "path": "/",
        "hostOnly": false,
        "creation": "2022-11-30T15:49:53.988Z",
        "lastAccessed": "2022-11-30T15:49:53.988Z"
    },
    {
        "key": "wd",
        "value": "384x727",
        "domain": "facebook.com",
        "path": "/",
        "hostOnly": false,
        "creation": "2022-11-30T15:49:53.988Z",
        "lastAccessed": "2022-11-30T15:49:53.988Z"
    },
    {
        "key": "locale",
        "value": "vi_VN",
        "domain": "facebook.com",
        "path": "/",
        "hostOnly": false,
        "creation": "2022-11-30T15:49:53.988Z",
        "lastAccessed": "2022-11-30T15:49:53.988Z"
    },
    {
        "key": "fbl_st",
        "value": "101432561%3BT%3A27830389",
        "domain": "facebook.com",
        "path": "/",
        "hostOnly": false,
        "creation": "2022-11-30T15:49:53.988Z",
        "lastAccessed": "2022-11-30T15:49:53.988Z"
    },
    {
        "key": "fbl_cs",
        "value": "AhBV322EzW9hrs7SVIJHqMlKGDRBQ3Zqak1PPXEwaUVTQkxyaU1QdXJxRg",
        "domain": "facebook.com",
        "path": "/",
        "hostOnly": false,
        "creation": "2022-11-30T15:49:53.988Z",
        "lastAccessed": "2022-11-30T15:49:53.988Z"
    },
    {
        "key": "fbl_ci",
        "value": "1803599553173797",
        "domain": "facebook.com",
        "path": "/",
        "hostOnly": false,
        "creation": "2022-11-30T15:49:53.988Z",
        "lastAccessed": "2022-11-30T15:49:53.988Z"
    },
    {
        "key": "vpd",
        "value": "v1%3B682x384x1.875",
        "domain": "facebook.com",
        "path": "/",
        "hostOnly": false,
        "creation": "2022-11-30T15:49:53.988Z",
        "lastAccessed": "2022-11-30T15:49:53.988Z"
    }
]
